{
	"info": {
		"_postman_id": "542bdbf2-7901-4d51-96e3-b0b95c173197",
		"name": "Vitalink V2",
		"schema": "https://schema.getpostman.com/json/collection/v2.1.0/collection.json",
		"_exporter_id": "619775"
	},
	"item": [
		{
			"name": "GENERAL",
			"item": [
				{
					"name": "Auth",
					"item": [
						{
							"name": "Register && Login",
							"item": [
								{
									"name": "Login User - Super Admin",
									"request": {
										"method": "POST",
										"header": [
											{
												"key": "x-api-key",
												"value": "{{secret_api_key}}",
												"type": "text"
											},
											{
												"key": "device-info",
												"value": "{\"userAgent\":\"Mozilla/5.0 (Linux; Android 10; SM-G973F Build/QP1A.190711.020; wv) AppleWebKit/537.36 (KHTML, like Gecko) Version/4.0 Chrome/88.0.4324.152 Mobile Safari/537.36\",\"platform\":\"Android\",\"environment\":\"Mobile\",\"language\":\"en-US\",\"screenResolution\":\"1080x2280\"}",
												"type": "text"
											}
										],
										"body": {
											"mode": "raw",
											"raw": "{\r\n  \"email\": \"vitalinkcr2@gmail.com\",\r\n  \"user_name\": null,\r\n  \"password\": \"VitalinkCR2*\"\r\n}\r\n\r\n",
											"options": {
												"raw": {
													"language": "json"
												}
											}
										},
										"url": {
											"raw": "{{host}}/auth/login",
											"host": [
												"{{host}}"
											],
											"path": [
												"auth",
												"login"
											]
										}
									},
									"response": []
								},
								{
									"name": "Login User - Customer",
									"request": {
										"method": "POST",
										"header": [
											{
												"key": "x-api-key",
												"value": "{{secret_api_key}}",
												"type": "text"
											},
											{
												"key": "device-info",
												"value": "{\"userAgent\":\"Mozilla/5.0 (Linux; Android 10; SM-G973F Build/QP1A.190711.020; wv) AppleWebKit/537.36 (KHTML, like Gecko) Version/4.0 Chrome/88.0.4324.152 Mobile Safari/537.36\",\"platform\":\"Android\",\"environment\":\"Mobile\",\"language\":\"en-US\",\"screenResolution\":\"1080x2280\"}",
												"type": "text"
											}
										],
										"body": {
											"mode": "raw",
											"raw": "{\r\n  \"email\": \"lfernandez@example.com\",\r\n  \"user_name\": null,\r\n  \"password\": \"Vitatest25*\"\r\n}\r\n\r\n",
											"options": {
												"raw": {
													"language": "json"
												}
											}
										},
										"url": {
											"raw": "{{host}}/auth/login",
											"host": [
												"{{host}}"
											],
											"path": [
												"auth",
												"login"
											]
										}
									},
									"response": []
								},
								{
									"name": "Login User - Finance Entity",
									"request": {
										"method": "POST",
										"header": [
											{
												"key": "x-api-key",
												"value": "{{secret_api_key}}",
												"type": "text"
											}
										],
										"body": {
											"mode": "raw",
											"raw": "{\r\n  \"email\": \"fabian7593+test1@gmail.com\",\r\n  \"password\": \"Cbiblica77@gmail.com\"\r\n}\r\n\r\n",
											"options": {
												"raw": {
													"language": "json"
												}
											}
										},
										"url": {
											"raw": "{{host}}/auth/login",
											"host": [
												"{{host}}"
											],
											"path": [
												"auth",
												"login"
											]
										}
									},
									"response": []
								},
								{
									"name": "Login User - Legal Representative",
									"request": {
										"method": "POST",
										"header": [
											{
												"key": "x-api-key",
												"value": "{{secret_api_key}}",
												"type": "text"
											}
										],
										"body": {
											"mode": "raw",
											"raw": "{\r\n  \"email\": \"gulate@example.com\",\r\n  \"password\": \"Vitatest25*\"\r\n}\r\n\r\n",
											"options": {
												"raw": {
													"language": "json"
												}
											}
										},
										"url": {
											"raw": "{{host}}/auth/login",
											"host": [
												"{{host}}"
											],
											"path": [
												"auth",
												"login"
											]
										}
									},
									"response": []
								},
								{
									"name": "Logout",
									"request": {
										"method": "POST",
										"header": [
											{
												"key": "authorization",
												"value": "{{auth_jwt}}",
												"type": "text"
											},
											{
												"key": "x-api-key",
												"value": "{{secret_api_key}}",
												"type": "text"
											}
										],
										"url": {
											"raw": "{{host}}/auth/logout",
											"host": [
												"{{host}}"
											],
											"path": [
												"auth",
												"logout"
											]
										}
									},
									"response": []
								},
								{
									"name": "Register - Finance Entity",
									"request": {
										"method": "POST",
										"header": [
											{
												"key": "x-api-key",
												"value": "{{secret_api_key}}",
												"type": "text"
											}
										],
										"body": {
											"mode": "raw",
											"raw": "{\r\n  \"card_id\": \"7777777\",\r\n  \"id_type\":\"PHYSICAL_DNI\", // PHYSICAL_DNI, JURIDICAL_DNI, DIMEX, PASSPORT\r\n  \"name\": \"Clinica Biblica\",\r\n  \"email\": \"fabian7593+test4@gmail.com\",\r\n  \"password\": \"Fabian7593+test4@gmail.com\",\r\n  \"gender\": \"O\", // \"M,\"F\",\"O\"\r\n  \"role_code\" : \"FINANCE_ENTITY\" // \"CUSTOMER\",\r\n  //\"finance_entity\": \"a232-b42c-sd2h-87ce\" \r\n  //\"user_name\": \"\" //CAN LOGIN WITH THIS\r\n  //\"phone_number\": \"\",\r\n  //\"birth_date\": \"\",\r\n  //\"country_iso_code\": \"\",\r\n  //\"province\": \"\",\r\n  //\"address\": \"\",\r\n  //\"city_name\": \"\",\r\n  //\"postal_code\": \"\",\r\n  //\"latitude\": \"10.12301023\",\r\n  //\"longitude\": \"-9.12341212\",\r\n  //\"profile_picture_url\": \"\",\r\n  \r\n}\r\n\r\n",
											"options": {
												"raw": {
													"language": "json"
												}
											}
										},
										"url": {
											"raw": "{{host}}/auth/register",
											"host": [
												"{{host}}"
											],
											"path": [
												"auth",
												"register"
											]
										}
									},
									"response": []
								},
								{
									"name": "Recover User By Email",
									"request": {
										"method": "POST",
										"header": [
											{
												"key": "x-api-key",
												"value": "{{secret_api_key}}",
												"type": "text"
											}
										],
										"body": {
											"mode": "raw",
											"raw": "{\r\n  \"email\": \"fabian7593@gmail.com\"\r\n}\r\n\r\n",
											"options": {
												"raw": {
													"language": "json"
												}
											}
										},
										"url": {
											"raw": "{{host}}/auth/recover_user",
											"host": [
												"{{host}}"
											],
											"path": [
												"auth",
												"recover_user"
											]
										}
									},
									"response": []
								},
								{
									"name": "Confirmation Register",
									"request": {
										"method": "GET",
										"header": [],
										"url": {
											"raw": "{{host}}/confirmation_register/eyJhbGciOiJIUzI1NiIsInR5cCI6IkpXVCJ9.eyJpZCI6MCwiZW1haWwiOiJmYWJpYW43NTkzQGdtYWlsLmNvbSIsInJvbGUiOiJBRE1JTiIsImlhdCI6MTcxNDYzMTgwOX0.YO7pkH6x0dLm_xp5i9E2x8tWir-gYeh1t09sKrD-kNA",
											"host": [
												"{{host}}"
											],
											"path": [
												"confirmation_register",
												"eyJhbGciOiJIUzI1NiIsInR5cCI6IkpXVCJ9.eyJpZCI6MCwiZW1haWwiOiJmYWJpYW43NTkzQGdtYWlsLmNvbSIsInJvbGUiOiJBRE1JTiIsImlhdCI6MTcxNDYzMTgwOX0.YO7pkH6x0dLm_xp5i9E2x8tWir-gYeh1t09sKrD-kNA"
											]
										}
									},
									"response": []
								}
							]
						},
						{
							"name": "Tokens",
							"item": [
								{
									"name": "Refresh Token",
									"protocolProfileBehavior": {
										"disableBodyPruning": true
									},
									"request": {
										"method": "GET",
										"header": [
											{
												"key": "x-api-key",
												"value": "{{secret_api_key}}",
												"type": "text"
											}
										],
										"body": {
											"mode": "raw",
											"raw": "{\r\n  \"email\": \"limelandcompanycr@gmail.com\",\r\n  \"password\": \"limelandcompanycr\"\r\n}\r\n\r\n",
											"options": {
												"raw": {
													"language": "json"
												}
											}
										},
										"url": {
											"raw": "{{host}}/refresh_token/eyJhbGciOiJIUzI1NiIsInR5cCI6IkpXVCJ9.eyJpZCI6ImE5YTZjMGM0LTg1MGMtNDBmZS04NzlkLTQwYTc4MmM5MjlhZCIsImVtYWlsIjoic2FtYmFzb2NjZXIyNEBnbWFpbC5jb20iLCJyb2xlIjoiOWIxZTZjNGEtNGNiNi00ZmYzLTlhNDQtMmRlOGQyNDUxMDRhIiwiaWF0IjoxNzMxMzA5NTAwLCJleHAiOjE3MzEzOTU5MDB9.XwR1YaeU_kocb3wnQ7yfDTbUu5EEQiu0KwLEohpfm9I",
											"host": [
												"{{host}}"
											],
											"path": [
												"refresh_token",
												"eyJhbGciOiJIUzI1NiIsInR5cCI6IkpXVCJ9.eyJpZCI6ImE5YTZjMGM0LTg1MGMtNDBmZS04NzlkLTQwYTc4MmM5MjlhZCIsImVtYWlsIjoic2FtYmFzb2NjZXIyNEBnbWFpbC5jb20iLCJyb2xlIjoiOWIxZTZjNGEtNGNiNi00ZmYzLTlhNDQtMmRlOGQyNDUxMDRhIiwiaWF0IjoxNzMxMzA5NTAwLCJleHAiOjE3MzEzOTU5MDB9.XwR1YaeU_kocb3wnQ7yfDTbUu5EEQiu0KwLEohpfm9I"
											]
										}
									},
									"response": []
								}
							]
						},
						{
							"name": "Forgot Password",
							"item": [
								{
									"name": "Forgot Password",
									"request": {
										"method": "POST",
										"header": [
											{
												"key": "x-api-key",
												"value": "{{secret_api_key}}",
												"type": "text"
											}
										],
										"body": {
											"mode": "raw",
											"raw": "{\r\n  \"email\": \"fabian7593@gmail.com\"\r\n}\r\n\r\n",
											"options": {
												"raw": {
													"language": "json"
												}
											}
										},
										"url": {
											"raw": "{{host}}/forgot_password",
											"host": [
												"{{host}}"
											],
											"path": [
												"forgot_password"
											]
										}
									},
									"response": []
								},
								{
									"name": "Reset Password",
									"request": {
										"method": "POST",
										"header": [
											{
												"key": "x-api-key",
												"value": "{{secret_api_key}}",
												"type": "text"
											}
										],
										"body": {
											"mode": "raw",
											"raw": "{\r\n  \"password\": \"Tenshitest3@gmail.com\"\r\n}\r\n\r\n",
											"options": {
												"raw": {
													"language": "json"
												}
											}
										},
										"url": {
											"raw": "{{host}}/reset_password/eyJhbGciOiJIUzI1NiIsInR5cCI6IkpXVCJ9.eyJlbWFpbCI6InRlbnNoaXRlc3QzQGdtYWlsLmNvbSIsImlhdCI6MTcyNzY4MjQ0NiwiZXhwIjoxNzI3NjgzMzQ2fQ.TFQyQIMBmYOpX3QS7EPymjsd67uPkpNZGbsY3BKi8_M",
											"host": [
												"{{host}}"
											],
											"path": [
												"reset_password",
												"eyJhbGciOiJIUzI1NiIsInR5cCI6IkpXVCJ9.eyJlbWFpbCI6InRlbnNoaXRlc3QzQGdtYWlsLmNvbSIsImlhdCI6MTcyNzY4MjQ0NiwiZXhwIjoxNzI3NjgzMzQ2fQ.TFQyQIMBmYOpX3QS7EPymjsd67uPkpNZGbsY3BKi8_M"
											]
										}
									},
									"response": []
								},
								{
									"name": "Verify Token Forgot Password",
									"request": {
										"method": "GET",
										"header": [
											{
												"key": "x-api-key",
												"value": "{{secret_api_key}}",
												"type": "text"
											}
										],
										"url": {
											"raw": "{{host}}/verify_forgot_password/eyJhbGciOiJIUzI1NiIsInR5cCI6IkpXVCJ9.eyJlbWFpbCI6ImZhYmlhbjc1OTNAZ21haWwuY29tIiwiaWF0IjoxNzIxOTU3NDg5LCJleHAiOjE3MjE5NTgzODl9.qBh4l0pXJqun0fji8dYNVs4j8sIZdCJ58pQOamkcWAs",
											"host": [
												"{{host}}"
											],
											"path": [
												"verify_forgot_password",
												"eyJhbGciOiJIUzI1NiIsInR5cCI6IkpXVCJ9.eyJlbWFpbCI6ImZhYmlhbjc1OTNAZ21haWwuY29tIiwiaWF0IjoxNzIxOTU3NDg5LCJleHAiOjE3MjE5NTgzODl9.qBh4l0pXJqun0fji8dYNVs4j8sIZdCJ58pQOamkcWAs"
											]
										}
									},
									"response": []
								}
							]
						}
					]
				},
				{
					"name": "Users",
					"item": [
						{
							"name": "CRUD Users",
							"item": [
								{
									"name": "Insert User",
									"request": {
										"method": "POST",
										"header": [
											{
												"key": "authorization",
												"value": "{{auth_jwt}}",
												"type": "text"
											},
											{
												"key": "x-api-key",
												"value": "{{secret_api_key}}",
												"type": "text"
											}
										],
										"body": {
											"mode": "raw",
											"raw": "{\r\n  \"card_id\": 11111111,\r\n  \"first_name\": \"Fabian\",\r\n  \"last_name\": \"Rosales\",\r\n  \"email\": \"fabianr7593@gmail.com\",\r\n  \"password\": \"Fabianr7593@gmail.com\",\r\n  \"position\":\"Senior Software Developer\",\r\n  \"bio\":\"My personal Bio\",\r\n  \"phone_number\":\"+506 83461166\",\r\n  \"birth_date\": \"1993-05--7\",\r\n  \"gender\": \"M\",\r\n  \"country_iso_code\": \"CRC\",\r\n  \"city_name\":\"San Jose\",\r\n  \"postal_code\":\"10301\",\r\n  \"latitude\": 37.774929,\r\n  \"longitude\": -122.419418,\r\n  \"language\":\"es\",\r\n  \"profile_picture_url\":null,\r\n  \"role_code\": \"ab67f164-8950-453a-9ead-13697a29fed9\",\r\n  \"is_active_from_email\" : true,\r\n  \"account_status\":\"active\"\r\n}\r\n\r\n",
											"options": {
												"raw": {
													"language": "json"
												}
											}
										},
										"url": {
											"raw": "{{host}}/user/add",
											"host": [
												"{{host}}"
											],
											"path": [
												"user",
												"add"
											]
										}
									},
									"response": []
								},
								{
									"name": "Update User",
									"request": {
										"method": "PUT",
										"header": [
											{
												"key": "authorization",
												"value": "{{auth_jwt}}",
												"type": "text"
											},
											{
												"key": "x-api-key",
												"value": "{{secret_api_key}}",
												"type": "text"
											}
										],
										"body": {
											"mode": "raw",
											"raw": "{\r\n  \"card_id\": 7777,\r\n  \"first_name\": \"Test new user\",\r\n  \"position\":\"job position\",\r\n  \"phone_number\":\"+100 65432 - 3123\",\r\n  \"birth_date\": \"1990-05-20\"\r\n}\r\n\r\n",
											"options": {
												"raw": {
													"language": "json"
												}
											}
										},
										"url": {
											"raw": "{{host}}/user/edit?id=783ae704-73b8-479c-be37-e75418ae0b16",
											"host": [
												"{{host}}"
											],
											"path": [
												"user",
												"edit"
											],
											"query": [
												{
													"key": "id",
													"value": "783ae704-73b8-479c-be37-e75418ae0b16"
												}
											]
										}
									},
									"response": []
								},
								{
									"name": "Get User By Id",
									"request": {
										"method": "GET",
										"header": [
											{
												"key": "authorization",
												"value": "{{auth_jwt}}",
												"type": "text"
											},
											{
												"key": "x-api-key",
												"value": "{{secret_api_key}}",
												"type": "text"
											}
										],
										"url": {
											"raw": "{{host}}/user/get?id=bc166f73-048f-4c28-9593-ffa774416f29",
											"host": [
												"{{host}}"
											],
											"path": [
												"user",
												"get"
											],
											"query": [
												{
													"key": "id",
													"value": "bc166f73-048f-4c28-9593-ffa774416f29"
												}
											]
										}
									},
									"response": []
								},
								{
									"name": "Get Users",
									"request": {
										"method": "GET",
										"header": [
											{
												"key": "authorization",
												"value": "{{auth_jwt}}",
												"type": "text"
											},
											{
												"key": "x-api-key",
												"value": "{{secret_api_key}}",
												"type": "text"
											}
										],
										"url": {
											"raw": "{{host}}/user/get_all?size=3",
											"host": [
												"{{host}}"
											],
											"path": [
												"user",
												"get_all"
											],
											"query": [
												{
													"key": "size",
													"value": "3"
												}
											]
										}
									},
									"response": []
								},
								{
									"name": "Delete User",
									"request": {
										"method": "DELETE",
										"header": [
											{
												"key": "authorization",
												"value": "{{auth_jwt}}",
												"type": "text"
											},
											{
												"key": "x-api-key",
												"value": "{{secret_api_key}}",
												"type": "text"
											}
										],
										"url": {
											"raw": "{{host}}/user/delete?id=783ae704-73b8-479c-be37-e75418ae0b16",
											"host": [
												"{{host}}"
											],
											"path": [
												"user",
												"delete"
											],
											"query": [
												{
													"key": "id",
													"value": "783ae704-73b8-479c-be37-e75418ae0b16"
												}
											]
										}
									},
									"response": []
								}
							]
						}
					]
				},
				{
					"name": "Udcs",
					"item": [
						{
							"name": "Insert UDC",
							"request": {
								"method": "POST",
								"header": [
									{
										"key": "authorization",
										"value": "{{auth_jwt}}",
										"type": "text"
									},
									{
										"key": "x-api-key",
										"value": "{{secret_api_key}}",
										"type": "text"
									}
								],
								"body": {
									"mode": "raw",
									"raw": "{\r\n  \"code\": \"CLUSTER7777\",\r\n  \"type\": \"EVENT_TYPES\",\r\n  \"name\": \"Cluster\",\r\n  \"description\": \"Cluster\",\r\n  \"value1\": \"Cluster\",\r\n  \"value2\": \"valor_del_value2\"\r\n}\r\n\r\n\r\n",
									"options": {
										"raw": {
											"language": "json"
										}
									}
								},
								"url": {
									"raw": "{{host}}/udc/add",
									"host": [
										"{{host}}"
									],
									"path": [
										"udc",
										"add"
									]
								}
							},
							"response": []
						},
						{
							"name": "Update UDC",
							"request": {
								"method": "PUT",
								"header": [
									{
										"key": "authorization",
										"value": "{{auth_jwt}}",
										"type": "text"
									},
									{
										"key": "x-api-key",
										"value": "{{secret_api_key}}",
										"type": "text"
									}
								],
								"body": {
									"mode": "raw",
									"raw": "{\r\n  \"name\": \"Cluster Updated\",\r\n  \"description\": \"Cluster Updated\"\r\n}\r\n\r\n\r\n",
									"options": {
										"raw": {
											"language": "json"
										}
									}
								},
								"url": {
									"raw": "{{host}}/udc/edit?id=13",
									"host": [
										"{{host}}"
									],
									"path": [
										"udc",
										"edit"
									],
									"query": [
										{
											"key": "id",
											"value": "13"
										}
									]
								}
							},
							"response": []
						},
						{
							"name": "Delete UDC",
							"request": {
								"method": "DELETE",
								"header": [
									{
										"key": "authorization",
										"value": "{{auth_jwt}}",
										"type": "text"
									},
									{
										"key": "x-api-key",
										"value": "{{secret_api_key}}",
										"type": "text"
									}
								],
								"url": {
									"raw": "{{host}}/udc/delete?id=13",
									"host": [
										"{{host}}"
									],
									"path": [
										"udc",
										"delete"
									],
									"query": [
										{
											"key": "id",
											"value": "13"
										}
									]
								}
							},
							"response": []
						},
						{
							"name": "Get All UDC",
							"request": {
								"method": "GET",
								"header": [
									{
										"key": "authorization",
										"value": "{{auth_jwt}}",
										"type": "text"
									},
									{
										"key": "x-api-key",
										"value": "{{secret_api_key}}",
										"type": "text"
									}
								],
								"url": {
									"raw": "{{host}}/udc/get_all",
									"host": [
										"{{host}}"
									],
									"path": [
										"udc",
										"get_all"
									]
								}
							},
							"response": []
						},
						{
							"name": "Get All UDC With Filters",
							"request": {
								"method": "GET",
								"header": [
									{
										"key": "authorization",
										"value": "{{auth_jwt}}",
										"type": "text"
									},
									{
										"key": "x-api-key",
										"value": "{{secret_api_key}}",
										"type": "text"
									}
								],
								"url": {
									"raw": "{{host}}/udc/get_all?type=APPOINTMENT_RESULT",
									"host": [
										"{{host}}"
									],
									"path": [
										"udc",
										"get_all"
									],
									"query": [
										{
											"key": "code",
											"value": "PENDING",
											"disabled": true
										},
										{
											"key": "id",
											"value": "1",
											"disabled": true
										},
										{
											"key": "father_code",
											"value": "OPHTHALMOLOGY",
											"disabled": true
										},
										{
											"key": "type",
											"value": "MEDICAL_PROCEDURE",
											"disabled": true
										},
										{
											"key": "size",
											"value": "5",
											"disabled": true
										},
										{
											"key": "type",
											"value": "APPOINTMENT_RESULT"
										}
									]
								}
							},
							"response": []
						}
					]
				},
				{
					"name": "Documents",
					"item": [
						{
							"name": "Insert Document",
							"request": {
								"method": "POST",
								"header": [
									{
										"key": "authorization",
										"value": "{{auth_jwt}}",
										"type": "text"
									},
									{
										"key": "x-api-key",
										"value": "{{secret_api_key}}",
										"type": "text"
									}
								],
								"body": {
									"mode": "formdata",
									"formdata": [
										{
											"key": "file",
											"type": "file",
											"src": "/C:/Users/fabia/OneDrive/Escritorio/1744935316612 (3).png"
										},
										{
											"key": "fields",
											"value": "{\"title\":\"Front end SSS\",\"type\": \"IMG\", \"description\": \"PROFILE PICTURE\", \"id_for_table\": 3, \"table\": \"SUPPLIER\",  \"action_type\":  \"PROFILE_PICTURE\", \"user_id\": \"28ed40ad-3cc3-42c0-af9c-86d18c926bd7\", \"is_public\":1}",
											"type": "text"
										},
										{
											"key": "",
											"value": "",
											"type": "text",
											"disabled": true
										},
										{
											"key": "",
											"value": "",
											"type": "text",
											"disabled": true
										}
									]
								},
								"url": {
									"raw": "{{host}}/document/add",
									"host": [
										"{{host}}"
									],
									"path": [
										"document",
										"add"
									]
								}
							},
							"response": []
						},
						{
							"name": "Get Private Document by Code",
							"request": {
								"method": "GET",
								"header": [
									{
										"key": "authorization",
										"value": "{{auth_jwt}}",
										"type": "text"
									},
									{
										"key": "x-api-key",
										"value": "{{secret_api_key}}",
										"type": "text"
									}
								],
								"url": {
									"raw": "{{host}}/document/get_by_code?code=PROFILE_PICTURE__USER__1__DOC__1942025184731",
									"host": [
										"{{host}}"
									],
									"path": [
										"document",
										"get_by_code"
									],
									"query": [
										{
											"key": "code",
											"value": "PROFILE_PICTURE__USER__1__DOC__1942025184731"
										}
									]
								}
							},
							"response": []
						},
						{
							"name": "Get Documents",
							"request": {
								"method": "GET",
								"header": [
									{
										"key": "authorization",
										"value": "{{auth_jwt}}",
										"type": "text"
									},
									{
										"key": "x-api-key",
										"value": "{{secret_api_key}}",
										"type": "text"
									}
								],
								"url": {
									"raw": "{{host}}/document/get_all",
									"host": [
										"{{host}}"
									],
									"path": [
										"document",
										"get_all"
									]
								}
							},
							"response": []
						},
						{
							"name": "Get Documents By Some Params",
							"request": {
								"method": "GET",
								"header": [
									{
										"key": "authorization",
										"value": "{{auth_jwt}}",
										"type": "text"
									},
									{
										"key": "x-api-key",
										"value": "{{secret_api_key}}",
										"type": "text"
									}
								],
								"url": {
									"raw": "{{host}}/document/get_by_filters?table=SUPPLIER&id_for_table=3&action_type=GENERAL_GALLERY",
									"host": [
										"{{host}}"
									],
									"path": [
										"document",
										"get_by_filters"
									],
									"query": [
										{
											"key": "table",
											"value": "SUPPLIER"
										},
										{
											"key": "user_id",
											"value": "3",
											"disabled": true
										},
										{
											"key": "id_for_table",
											"value": "3"
										},
										{
											"key": "name",
											"value": null,
											"disabled": true
										},
										{
											"key": "ext",
											"value": null,
											"disabled": true
										},
										{
											"key": "action_type",
											"value": "GENERAL_GALLERY",
											"description": "PROFILE_PICTURE, GENERAL_GALLERY, PERSONAL_DOCUMENT, PRIVATE_CONTRACT, MEDICAL_PROCEDURE_ATTACHMENT, OTHER"
										},
										{
											"key": "type",
											"value": "",
											"description": "DOC, IMG, OTHER",
											"disabled": true
										}
									]
								}
							},
							"response": []
						},
						{
							"name": "Delete Document",
							"request": {
								"method": "DELETE",
								"header": [
									{
										"key": "authorization",
										"value": "{{auth_jwt}}",
										"type": "text"
									},
									{
										"key": "x-api-key",
										"value": "{{secret_api_key}}",
										"type": "text"
									}
								],
								"url": {
									"raw": "{{host}}/document/delete?id=2",
									"host": [
										"{{host}}"
									],
									"path": [
										"document",
										"delete"
									],
									"query": [
										{
											"key": "id",
											"value": "2"
										}
									]
								}
							},
							"response": []
						},
						{
							"name": "Update Document",
							"request": {
								"method": "PUT",
								"header": [
									{
										"key": "authorization",
										"value": "{{auth_jwt}}",
										"type": "text"
									},
									{
										"key": "x-api-key",
										"value": "{{secret_api_key}}",
										"type": "text"
									}
								],
								"body": {
									"mode": "formdata",
									"formdata": [
										{
											"key": "file",
											"type": "file",
											"src": "/C:/Users/johan/Downloads/Firma Correo AC (4).png"
										},
										{
											"key": "fields",
											"value": "{\"title\":\"name test\",\"type\": \"DOC\", \"description\": \"Descripción del documento\", \"id_for_table\": 2, \"table\": \"USER\",  \"action_type\":  \"PROFILE_PICTURE\", \"user_id\": 5, \"is_public\":0}",
											"type": "text"
										}
									]
								},
								"url": {
									"raw": "{{host}}/document/edit?id=2",
									"host": [
										"{{host}}"
									],
									"path": [
										"document",
										"edit"
									],
									"query": [
										{
											"key": "id",
											"value": "2"
										}
									]
								}
							},
							"response": []
						}
					]
				},
				{
					"name": "Emails",
					"item": [
						{
							"name": "Send Email By User Email",
							"request": {
								"method": "POST",
								"header": [
									{
										"key": "authorization",
										"value": "{{auth_jwt}}",
										"type": "text"
									},
									{
										"key": "x-api-key",
										"value": "{{secret_api_key}}",
										"type": "text"
									}
								],
								"body": {
									"mode": "raw",
									"raw": "{\r\n  \"subject\": \"This is an email test\",\r\n  \"body_message\": \"Body message, remember this use the emails template\",\r\n  \"email\": \"fabian7593@gmail.com\"\r\n}\r\n\r\n",
									"options": {
										"raw": {
											"language": "json"
										}
									}
								},
								"url": {
									"raw": "{{host}}/email/send_email",
									"host": [
										"{{host}}"
									],
									"path": [
										"email",
										"send_email"
									]
								}
							},
							"response": []
						},
						{
							"name": "Send Email All Users",
							"request": {
								"method": "POST",
								"header": [
									{
										"key": "authorization",
										"value": "{{auth_jwt}}",
										"type": "text"
									},
									{
										"key": "x-api-key",
										"value": "{{secret_api_key}}",
										"type": "text"
									}
								],
								"body": {
									"mode": "raw",
									"raw": "{\r\n  \"subject\": \"Esto es una prueba desde postman\",\r\n  \"body_message\": \"El ciego imagina todo aquello que no puede ver...\"\r\n}\r\n\r\n",
									"options": {
										"raw": {
											"language": "json"
										}
									}
								},
								"url": {
									"raw": "{{host}}/email/send_email_all_users",
									"host": [
										"{{host}}"
									],
									"path": [
										"email",
										"send_email_all_users"
									]
								}
							},
							"response": []
						}
					]
				},
				{
					"name": "Roles",
					"item": [
						{
							"name": "Get All Roles",
							"request": {
								"method": "GET",
								"header": [
									{
										"key": "authorization",
										"value": "{{auth_jwt}}",
										"type": "text"
									},
									{
										"key": "x-api-key",
										"value": "{{secret_api_key}}",
										"type": "text"
									}
								],
								"url": {
									"raw": "{{host}}/role/get_all",
									"host": [
										"{{host}}"
									],
									"path": [
										"role",
										"get_all"
									]
								}
							},
							"response": []
						}
					]
				},
				{
					"name": "Logs",
					"item": [
						{
							"name": "Insert Logs",
							"request": {
								"method": "POST",
								"header": [
									{
										"key": "authorization",
										"value": "{{auth_jwt}}",
										"type": "text"
									},
									{
										"key": "x-api-key",
										"value": "{{secret_api_key}}",
										"type": "text"
									}
								],
								"body": {
									"mode": "raw",
									"raw": "{\r\n    \"method\": \"login\",\r\n    \"class\": \"UserController\",\r\n    \"type\": \"Error\", \r\n    \"action\": \"Log Error\", \r\n    \"https\": 400,\r\n    \"message\": \"Specific error\",\r\n    \"description\": \"Desc\",\r\n    \"environment\": \"FrontEnd\"\r\n}\r\n",
									"options": {
										"raw": {
											"language": "json"
										}
									}
								},
								"url": {
									"raw": "{{host}}/log/add",
									"host": [
										"{{host}}"
									],
									"path": [
										"log",
										"add"
									]
								}
							},
							"response": []
						},
						{
							"name": "Get Logs",
							"request": {
								"method": "GET",
								"header": [
									{
										"key": "authorization",
										"value": "{{auth_jwt}}",
										"type": "text"
									},
									{
										"key": "x-api-key",
										"value": "{{secret_api_key}}",
										"type": "text"
									}
								],
								"url": {
									"raw": "{{host}}/log/get_by_filters?size=2&page=1",
									"host": [
										"{{host}}"
									],
									"path": [
										"log",
										"get_by_filters"
									],
									"query": [
										{
											"key": "size",
											"value": "2"
										},
										{
											"key": "page",
											"value": "1"
										}
									]
								}
							},
							"response": []
						}
					]
				}
			]
		},
		{
			"name": "VITALINK",
			"item": [
				{
					"name": "Location",
					"item": [
						{
							"name": "Create Location",
							"request": {
								"method": "POST",
								"header": [
									{
										"key": "authorization",
										"value": "{{auth_jwt}}",
										"type": "text"
									},
									{
										"key": "x-api-key",
										"value": "{{secret_api_key}}",
										"type": "text"
									}
								],
								"body": {
									"mode": "raw",
									"raw": "{\n  \"name\": \"Clinica Biblica Sede Central\"\n  //\"country_iso_code\": \"CRC\",\n  //\"province\": \"San Jose\",\n  //\"address\": \"Lorem\",\n  //\"city_name\": \"Lorem\",\n  //\"postal_code\": \"10301\",\n  //\"latitude\": \"10.0092312\",\n  //\"longitude\": \"-9.123443112\",\n  //\"finance_entity\": \"asd31-23232-dqwe\"\n}",
									"options": {
										"raw": {
											"language": "json"
										}
									}
								},
								"url": {
									"raw": "{{host}}/location/add",
									"host": [
										"{{host}}"
									],
									"path": [
										"location",
										"add"
									]
								}
							},
							"response": []
						},
						{
							"name": "Update Location",
							"request": {
								"method": "PUT",
								"header": [
									{
										"key": "authorization",
										"value": "{{auth_jwt}}",
										"type": "text"
									},
									{
										"key": "x-api-key",
										"value": "{{secret_api_key}}",
										"type": "text"
									}
								],
								"body": {
									"mode": "raw",
									"raw": "{\n  \"name\": \"Clinica Biblica Sede Central 2\",\n  //\"country_iso_code\": \"CRC\",\n  \"province\": \"San Jose\"\n  //\"address\": \"Lorem\",\n  //\"city_name\": \"Lorem\",\n  //\"postal_code\": \"10301\",\n  //\"latitude\": \"10.0092312\",\n  //\"longitude\": \"-9.123443112\",\n  //\"finance_entity\": \"asd31-23232-dqwe\"\n}",
									"options": {
										"raw": {
											"language": "json"
										}
									}
								},
								"url": {
									"raw": "{{host}}/location/edit?id=1",
									"host": [
										"{{host}}"
									],
									"path": [
										"location",
										"edit"
									],
									"query": [
										{
											"key": "id",
											"value": "1"
										}
									]
								}
							},
							"response": []
						},
						{
							"name": "Get Location by ID",
							"request": {
								"method": "GET",
								"header": [
									{
										"key": "authorization",
										"value": "{{auth_jwt}}",
										"type": "text"
									},
									{
										"key": "x-api-key",
										"value": "{{secret_api_key}}",
										"type": "text"
									}
								],
								"url": {
									"raw": "{{host}}/location/get?id=1",
									"host": [
										"{{host}}"
									],
									"path": [
										"location",
										"get"
									],
									"query": [
										{
											"key": "id",
											"value": "1"
										}
									]
								}
							},
							"response": []
						},
						{
							"name": "Get All Location",
							"request": {
								"method": "GET",
								"header": [
									{
										"key": "authorization",
										"value": "{{auth_jwt}}",
										"type": "text"
									},
									{
										"key": "x-api-key",
										"value": "{{secret_api_key}}",
										"type": "text"
									}
								],
								"url": {
									"raw": "{{host}}/location/get_all",
									"host": [
										"{{host}}"
									],
									"path": [
										"location",
										"get_all"
									]
								}
							},
							"response": []
						},
						{
							"name": "Delete Location",
							"request": {
								"method": "DELETE",
								"header": [
									{
										"key": "authorization",
										"value": "{{auth_jwt}}",
										"type": "text"
									},
									{
										"key": "x-api-key",
										"value": "{{secret_api_key}}",
										"type": "text"
									}
								],
								"url": {
									"raw": "{{host}}/location/delete?id=1",
									"host": [
										"{{host}}"
									],
									"path": [
										"location",
										"delete"
									],
									"query": [
										{
											"key": "id",
											"value": "1"
										}
									]
								}
							},
							"response": []
						}
					]
				},
				{
					"name": "Supplier",
					"item": [
						{
							"name": "Create Supplier",
							"request": {
								"method": "POST",
								"header": [
									{
										"key": "authorization",
										"value": "{{auth_jwt}}",
										"type": "text"
									},
									{
										"key": "x-api-key",
										"value": "{{secret_api_key}}",
										"type": "text"
									}
								],
								"body": {
									"mode": "raw",
									"raw": "{\n  \"id_type\": \"PHYSICAL_DNI\",\n  \"card_id\": \"12345678X\",\n  \"email\": \"juan.perez@hospitalcentral.com\",\n  \"medical_type_code\": \"GENERAL_MEDICAL\",\n  \"legal_representative\": \"d0b47084-2888-4e7e-9347-0aa62fb6aa8f\"\n  //\"num_medical_enrollment\": \"MED-987654\",\n  //\"name\": \"Dr. Juan Pérez\",\n  //\"phone_number\": \"+506 11 2345-6789\",\n  //\"country_iso_code\": \"CRC\",\n  //\"province\": \"San Jose\",\n  //\"city_name\": \"Guadalupe\",\n  //\"postal_code\": \"1301\",\n  //\"profile_picture_url\": \"https://hospitalcentral.com/profiles/juan_perez.jpg\",\n  //\"description\": \"Especialista en cirugía general con más de 10 años de experiencia en hospitales de alto nivel.\",\n  //\"address\": \"Av. 13 y Calle 50\",\n  //\"street_number\": \"123\",\n  //\"floor\": \"5\",\n  //\"door_number\": \"A\",\n  //\"latitude\": \"-34.9215\",\n  //\"longitude\": \"-57.9545\",\n  //\"experience_years\": \"15\",\n  //\"patients_number\": \"5000\",\n  //\"is_hospital\": false,\n  //\"our_history\": \"Fundada en 2005, nuestra clínica ha atendido a más de 50,000 pacientes.\",\n  //\"mission\": \"Brindar atención médica de calidad con un enfoque humanitario.\",\n  //\"vision\": \"Ser un referente en salud en Latinoamérica.\",\n  //\"code_card_id_file\": \"ID12345678X\",\n  //\"code_medical_license_file\": \"MED-987654\",\n  //\"gender\": \"M\"\n}\n",
									"options": {
										"raw": {
											"language": "json"
										}
									}
								},
								"url": {
									"raw": "{{host}}/supplier/add",
									"host": [
										"{{host}}"
									],
									"path": [
										"supplier",
										"add"
									]
								}
							},
							"response": []
						},
						{
							"name": "Update Supplier",
							"request": {
								"method": "PUT",
								"header": [
									{
										"key": "authorization",
										"value": "{{auth_jwt}}",
										"type": "text"
									},
									{
										"key": "x-api-key",
										"value": "{{secret_api_key}}",
										"type": "text"
									}
								],
								"body": {
									"mode": "raw",
									"raw": "{\n  //\"id_type\": \"PHYSICAL_DNI\",\n  //\"card_id\": \"12345678X\",\n  //\"email\": \"juan.perez@hospitalcentral.com\",\n  //\"medical_type_code\": \"GENERAL_MEDICAL\",\n  //\"legal_representative\": \"d0b47084-2888-4e7e-9347-0aa62fb6aa8f\",\n  //\"num_medical_enrollment\": \"MED-987654\",\n  \"name\": \"Dr. Juan Pérez\"\n  //\"phone_number\": \"+506 11 2345-6789\",\n  //\"country_iso_code\": \"CRC\",\n  //\"province\": \"San Jose\",\n  //\"city_name\": \"Guadalupe\",\n  //\"postal_code\": \"1301\",\n  //\"profile_picture_url\": \"https://hospitalcentral.com/profiles/juan_perez.jpg\",\n  //\"description\": \"Especialista en cirugía general con más de 10 años de experiencia en hospitales de alto nivel.\",\n  //\"address\": \"Av. 13 y Calle 50\",\n  //\"street_number\": \"123\",\n  //\"floor\": \"5\",\n  //\"door_number\": \"A\",\n  //\"latitude\": \"-34.9215\",\n  //\"longitude\": \"-57.9545\",\n  //\"experience_years\": \"15\",\n  //\"patients_number\": \"5000\",\n  //\"is_hospital\": false,\n  //\"our_history\": \"Fundada en 2005, nuestra clínica ha atendido a más de 50,000 pacientes.\",\n  //\"mission\": \"Brindar atención médica de calidad con un enfoque humanitario.\",\n  //\"vision\": \"Ser un referente en salud en Latinoamérica.\",\n  //\"code_card_id_file\": \"ID12345678X\",\n  //\"code_medical_license_file\": \"MED-987654\",\n  //\"gender\": \"M\"\n}\n",
									"options": {
										"raw": {
											"language": "json"
										}
									}
								},
								"url": {
									"raw": "{{host}}/supplier/edit?id=7",
									"host": [
										"{{host}}"
									],
									"path": [
										"supplier",
										"edit"
									],
									"query": [
										{
											"key": "id",
											"value": "7"
										}
									]
								}
							},
							"response": []
						},
						{
							"name": "Get Supplier by ID",
							"request": {
								"method": "GET",
								"header": [
									{
										"key": "authorization",
										"value": "{{auth_jwt}}",
										"type": "text"
									},
									{
										"key": "x-api-key",
										"value": "{{secret_api_key}}",
										"type": "text"
									}
								],
								"url": {
									"raw": "{{host}}/supplier/get?id=1",
									"host": [
										"{{host}}"
									],
									"path": [
										"supplier",
										"get"
									],
									"query": [
										{
											"key": "id",
											"value": "1"
										}
									]
								}
							},
							"response": []
						},
						{
							"name": "Get All Supplier",
							"request": {
								"method": "GET",
								"header": [
									{
										"key": "authorization",
										"value": "{{auth_jwt}}",
										"type": "text"
									},
									{
										"key": "x-api-key",
										"value": "{{secret_api_key}}",
										"type": "text"
									}
								],
								"url": {
									"raw": "{{host}}/supplier/get_all",
									"host": [
										"{{host}}"
									],
									"path": [
										"supplier",
										"get_all"
									]
								}
							},
							"response": []
						},
						{
							"name": "Get All Supplier Main",
							"request": {
								"method": "GET",
								"header": [
									{
										"key": "authorization",
										"value": "{{auth_jwt}}",
										"type": "text"
									},
									{
										"key": "x-api-key",
										"value": "{{secret_api_key}}",
										"type": "text"
									}
								],
								"url": {
									"raw": "{{host}}/supplier/get_all_main",
									"host": [
										"{{host}}"
									],
									"path": [
										"supplier",
										"get_all_main"
									],
									"query": [
										{
											"key": "specialty_code",
											"value": "DERMATOLOGY",
											"disabled": true
										},
										{
											"key": "procedure_code",
											"value": "REFRACTIVE_SURGERY",
											"disabled": true
										},
										{
											"key": "min_stars",
											"value": "5",
											"disabled": true
										},
										{
											"key": "province",
											"value": "Guanacaste",
											"disabled": true
										},
										{
											"key": "min_price",
											"value": "18000",
											"disabled": true
										},
										{
											"key": "max_price",
											"value": "25000",
											"disabled": true
										},
										{
											"key": "size",
											"value": "1",
											"disabled": true
										},
										{
											"key": "page",
											"value": "1",
											"disabled": true
										}
									]
								}
							},
							"response": []
						},
						{
							"name": "Delete Supplier",
							"request": {
								"method": "DELETE",
								"header": [
									{
										"key": "authorization",
										"value": "{{auth_jwt}}",
										"type": "text"
									},
									{
										"key": "x-api-key",
										"value": "{{secret_api_key}}",
										"type": "text"
									}
								],
								"url": {
									"raw": "{{host}}/supplier/delete?id=1",
									"host": [
										"{{host}}"
									],
									"path": [
										"supplier",
										"delete"
									],
									"query": [
										{
											"key": "id",
											"value": "1"
										}
									]
								}
							},
							"response": []
						}
					]
				},
				{
					"name": "SpecialtyBySupplier",
					"item": [
						{
							"name": "Create SpecialtyBySupplier",
							"request": {
								"method": "POST",
								"header": [
									{
										"key": "authorization",
										"value": "{{auth_jwt}}",
										"type": "text"
									},
									{
										"key": "x-api-key",
										"value": "{{secret_api_key}}",
										"type": "text"
									}
								],
								"body": {
									"mode": "raw",
									"raw": "{\n  \"supplier_id\": 7,\n  \"medical_specialty_code\": \"CARDIOLOGY\"\n}",
									"options": {
										"raw": {
											"language": "json"
										}
									}
								},
								"url": {
									"raw": "{{host}}/specialtybysupplier/add",
									"host": [
										"{{host}}"
									],
									"path": [
										"specialtybysupplier",
										"add"
									]
								}
							},
							"response": []
						},
						{
							"name": "Update SpecialtyBySupplier",
							"request": {
								"method": "PUT",
								"header": [
									{
										"key": "authorization",
										"value": "{{auth_jwt}}",
										"type": "text"
									},
									{
										"key": "x-api-key",
										"value": "{{secret_api_key}}",
										"type": "text"
									}
								],
								"body": {
									"mode": "raw",
									"raw": "{\n  \"supplier_id\": 7,\n  \"medical_specialty_code\": \"CARDIOLOGY\"\n}",
									"options": {
										"raw": {
											"language": "json"
										}
									}
								},
								"url": {
									"raw": "{{host}}/specialtybysupplier/edit?id=10",
									"host": [
										"{{host}}"
									],
									"path": [
										"specialtybysupplier",
										"edit"
									],
									"query": [
										{
											"key": "id",
											"value": "10"
										}
									]
								}
							},
							"response": []
						},
						{
							"name": "Get SpecialtyBySupplier by ID",
							"request": {
								"method": "GET",
								"header": [
									{
										"key": "authorization",
										"value": "{{auth_jwt}}",
										"type": "text"
									},
									{
										"key": "x-api-key",
										"value": "{{secret_api_key}}",
										"type": "text"
									}
								],
								"url": {
									"raw": "{{host}}/specialtybysupplier/get?id=10",
									"host": [
										"{{host}}"
									],
									"path": [
										"specialtybysupplier",
										"get"
									],
									"query": [
										{
											"key": "id",
											"value": "10"
										}
									]
								}
							},
							"response": []
						},
						{
							"name": "Get All SpecialtyBySupplier",
							"request": {
								"method": "GET",
								"header": [
									{
										"key": "authorization",
										"value": "{{auth_jwt}}",
										"type": "text"
									},
									{
										"key": "x-api-key",
										"value": "{{secret_api_key}}",
										"type": "text"
									}
								],
								"url": {
									"raw": "{{host}}/specialtybysupplier/get_all",
									"host": [
										"{{host}}"
									],
									"path": [
										"specialtybysupplier",
										"get_all"
									]
								}
							},
							"response": []
						},
						{
							"name": "Delete SpecialtyBySupplier",
							"request": {
								"method": "DELETE",
								"header": [
									{
										"key": "authorization",
										"value": "{{auth_jwt}}",
										"type": "text"
									},
									{
										"key": "x-api-key",
										"value": "{{secret_api_key}}",
										"type": "text"
									}
								],
								"url": {
									"raw": "{{host}}/specialtybysupplier/delete?id=1",
									"host": [
										"{{host}}"
									],
									"path": [
										"specialtybysupplier",
										"delete"
									],
									"query": [
										{
											"key": "id",
											"value": "1"
										}
									]
								}
							},
							"response": []
						}
					]
				},
				{
					"name": "ProcedureBySpecialty",
					"item": [
						{
							"name": "Create ProcedureBySpecialty",
							"request": {
								"method": "POST",
								"header": [
									{
										"key": "authorization",
										"value": "{{auth_jwt}}",
										"type": "text"
									},
									{
										"key": "x-api-key",
										"value": "{{secret_api_key}}",
										"type": "text"
									}
								],
								"body": {
									"mode": "raw",
									"raw": "{\n  \"specialty_id\": 10,\n  \"procedure_code\": \"CARDIO_INTERVENTION\"\n}",
									"options": {
										"raw": {
											"language": "json"
										}
									}
								},
								"url": {
									"raw": "{{host}}/procedurebyspecialty/add",
									"host": [
										"{{host}}"
									],
									"path": [
										"procedurebyspecialty",
										"add"
									]
								}
							},
							"response": []
						},
						{
							"name": "Update ProcedureBySpecialty",
							"request": {
								"method": "PUT",
								"header": [
									{
										"key": "authorization",
										"value": "{{auth_jwt}}",
										"type": "text"
									},
									{
										"key": "x-api-key",
										"value": "{{secret_api_key}}",
										"type": "text"
									}
								],
								"body": {
									"mode": "raw",
									"raw": "{\n  \"specialty_id\": 10,\n  \"procedure_code\": \"ECOCARDIOGRAMA\"\n}",
									"options": {
										"raw": {
											"language": "json"
										}
									}
								},
								"url": {
									"raw": "{{host}}/procedurebyspecialty/edit?id=1",
									"host": [
										"{{host}}"
									],
									"path": [
										"procedurebyspecialty",
										"edit"
									],
									"query": [
										{
											"key": "id",
											"value": "1"
										}
									]
								}
							},
							"response": []
						},
						{
							"name": "Get ProcedureBySpecialty by ID",
							"request": {
								"method": "GET",
								"header": [
									{
										"key": "authorization",
										"value": "{{auth_jwt}}",
										"type": "text"
									},
									{
										"key": "x-api-key",
										"value": "{{secret_api_key}}",
										"type": "text"
									}
								],
								"url": {
									"raw": "{{host}}/procedurebyspecialty/get?id=14",
									"host": [
										"{{host}}"
									],
									"path": [
										"procedurebyspecialty",
										"get"
									],
									"query": [
										{
											"key": "id",
											"value": "14"
										}
									]
								}
							},
							"response": []
						},
						{
							"name": "Get All ProcedureBySpecialty",
							"request": {
								"method": "GET",
								"header": [
									{
										"key": "authorization",
										"value": "{{auth_jwt}}",
										"type": "text"
									},
									{
										"key": "x-api-key",
										"value": "{{secret_api_key}}",
										"type": "text"
									}
								],
								"url": {
									"raw": "{{host}}/procedurebyspecialty/get_all",
									"host": [
										"{{host}}"
									],
									"path": [
										"procedurebyspecialty",
										"get_all"
									]
								}
							},
							"response": []
						},
						{
							"name": "Delete ProcedureBySpecialty",
							"request": {
								"method": "DELETE",
								"header": [
									{
										"key": "authorization",
										"value": "{{auth_jwt}}",
										"type": "text"
									},
									{
										"key": "x-api-key",
										"value": "{{secret_api_key}}",
										"type": "text"
									}
								],
								"url": {
									"raw": "{{host}}/procedurebyspecialty/delete?id=1",
									"host": [
										"{{host}}"
									],
									"path": [
										"procedurebyspecialty",
										"delete"
									],
									"query": [
										{
											"key": "id",
											"value": "1"
										}
									]
								}
							},
							"response": []
						}
					]
				},
				{
					"name": "Package",
					"item": [
						{
							"name": "Create Package",
							"request": {
								"method": "POST",
								"header": [
									{
										"key": "authorization",
										"value": "{{auth_jwt}}",
										"type": "text"
									},
									{
										"key": "x-api-key",
										"value": "{{secret_api_key}}",
										"type": "text"
									}
								],
								"body": {
									"mode": "raw",
									"raw": "{\n  \"procedure_by_specialty_id\": 14,\n  \"product_code\": \"CARDIO_CATH\"\n // \"discount\": 0,\n  /*\"services_offer\": \"  {\n    \"ASSESSMENT_DETAILS\": [\n        \"GENERAL_ANESTHESIA\",\n        \"REGIONAL_ANESTHESIA\",\n        \"POSTOP_PAIN_CONTROL\",\n        \"POSTOP_ULTRASOUND\",\n        \"POSTOP_CT\",\n        \"POSTOP_PHYSIOTHERAPY\"\n    ]\n  }\",*/\n}",
									"options": {
										"raw": {
											"language": "json"
										}
									}
								},
								"url": {
									"raw": "{{host}}/package/add",
									"host": [
										"{{host}}"
									],
									"path": [
										"package",
										"add"
									]
								}
							},
							"response": []
						},
						{
							"name": "Update Package",
							"request": {
								"method": "PUT",
								"header": [
									{
										"key": "authorization",
										"value": "{{auth_jwt}}",
										"type": "text"
									},
									{
										"key": "x-api-key",
										"value": "{{secret_api_key}}",
										"type": "text"
									}
								],
								"body": {
									"mode": "raw",
									"raw": "{\n  \"procedure_id\": 14,\n  \"product_code\": \"CARDIO_CATH\",\n  \"discount\": 0\n  /*\"services_offer\": \"  {\n    \"ASSESSMENT_DETAILS\": [\n        \"GENERAL_ANESTHESIA\",\n        \"REGIONAL_ANESTHESIA\",\n        \"POSTOP_PAIN_CONTROL\",\n        \"POSTOP_ULTRASOUND\",\n        \"POSTOP_CT\",\n        \"POSTOP_PHYSIOTHERAPY\"\n    ]\n  }\",*/\n}",
									"options": {
										"raw": {
											"language": "json"
										}
									}
								},
								"url": {
									"raw": "{{host}}/package/edit?id=1",
									"host": [
										"{{host}}"
									],
									"path": [
										"package",
										"edit"
									],
									"query": [
										{
											"key": "id",
											"value": "1"
										}
									]
								}
							},
							"response": []
						},
						{
							"name": "Get Package by ID",
							"request": {
								"method": "GET",
								"header": [
									{
										"key": "authorization",
										"value": "{{auth_jwt}}",
										"type": "text"
									},
									{
										"key": "x-api-key",
										"value": "{{secret_api_key}}",
										"type": "text"
									}
								],
								"url": {
									"raw": "{{host}}/package/get?id=16",
									"host": [
										"{{host}}"
									],
									"path": [
										"package",
										"get"
									],
									"query": [
										{
											"key": "id",
											"value": "16"
										}
									]
								}
							},
							"response": []
						},
						{
							"name": "Get All Package",
							"request": {
								"method": "GET",
								"header": [
									{
										"key": "authorization",
										"value": "{{auth_jwt}}",
										"type": "text"
									},
									{
										"key": "x-api-key",
										"value": "{{secret_api_key}}",
										"type": "text"
									}
								],
								"url": {
									"raw": "{{host}}/package/get_all",
									"host": [
										"{{host}}"
									],
									"path": [
										"package",
										"get_all"
									]
								}
							},
							"response": []
						},
						{
							"name": "Delete Package",
							"request": {
								"method": "DELETE",
								"header": [
									{
										"key": "authorization",
										"value": "{{auth_jwt}}",
										"type": "text"
									},
									{
										"key": "x-api-key",
										"value": "{{secret_api_key}}",
										"type": "text"
									}
								],
								"url": {
									"raw": "{{host}}/package/delete?id=1",
									"host": [
										"{{host}}"
									],
									"path": [
										"package",
										"delete"
									],
									"query": [
										{
											"key": "id",
											"value": "1"
										}
									]
								}
							},
							"response": []
						}
					]
				},
				{
					"name": "Availability",
					"item": [
						{
							"name": "Create Availability",
							"request": {
								"method": "POST",
								"header": [
									{
										"key": "authorization",
										"value": "{{auth_jwt}}",
										"type": "text"
									},
									{
										"key": "x-api-key",
										"value": "{{secret_api_key}}",
										"type": "text"
									}
								],
								"body": {
									"mode": "raw",
									"raw": "{\n  \"supplier_id\": 7,\n  \"location_id\": 3,\n  \"weekday\": \"MONDAY\",\n  \"from_hour\": \"08:00\",\n  \"to_hour\": \"14:00\"\n}",
									"options": {
										"raw": {
											"language": "json"
										}
									}
								},
								"url": {
									"raw": "{{host}}/availability/add",
									"host": [
										"{{host}}"
									],
									"path": [
										"availability",
										"add"
									]
								}
							},
							"response": []
						},
						{
							"name": "Update Availability",
							"request": {
								"method": "PUT",
								"header": [
									{
										"key": "authorization",
										"value": "{{auth_jwt}}",
										"type": "text"
									},
									{
										"key": "x-api-key",
										"value": "{{secret_api_key}}",
										"type": "text"
									}
								],
								"body": {
									"mode": "raw",
									"raw": "{\n  //\"supplier_id\": 7,\n  //\"location_id\": 3,\n  \"weekday\": \"FRIDAY\"\n  //\"from_hour\": \"08:00\",\n  //\"to_hour\": \"14:00\"\n}",
									"options": {
										"raw": {
											"language": "json"
										}
									}
								},
								"url": {
									"raw": "{{host}}/availability/edit?id=21",
									"host": [
										"{{host}}"
									],
									"path": [
										"availability",
										"edit"
									],
									"query": [
										{
											"key": "id",
											"value": "21"
										}
									]
								}
							},
							"response": []
						},
						{
							"name": "Get Availability by ID",
							"request": {
								"method": "GET",
								"header": [
									{
										"key": "authorization",
										"value": "{{auth_jwt}}",
										"type": "text"
									},
									{
										"key": "x-api-key",
										"value": "{{secret_api_key}}",
										"type": "text"
									}
								],
								"url": {
									"raw": "{{host}}/availability/get?id=1",
									"host": [
										"{{host}}"
									],
									"path": [
										"availability",
										"get"
									],
									"query": [
										{
											"key": "id",
											"value": "1"
										}
									]
								}
							},
							"response": []
						},
						{
							"name": "Get All Availability",
							"request": {
								"method": "GET",
								"header": [
									{
										"key": "authorization",
										"value": "{{auth_jwt}}",
										"type": "text"
									},
									{
										"key": "x-api-key",
										"value": "{{secret_api_key}}",
										"type": "text"
									}
								],
								"url": {
									"raw": "{{host}}/availability/get_all",
									"host": [
										"{{host}}"
									],
									"path": [
										"availability",
										"get_all"
									]
								}
							},
							"response": []
						},
						{
							"name": "Delete Availability",
							"request": {
								"method": "DELETE",
								"header": [
									{
										"key": "authorization",
										"value": "{{auth_jwt}}",
										"type": "text"
									},
									{
										"key": "x-api-key",
										"value": "{{secret_api_key}}",
										"type": "text"
									}
								],
								"url": {
									"raw": "{{host}}/availability/delete?id=1",
									"host": [
										"{{host}}"
									],
									"path": [
										"availability",
										"delete"
									],
									"query": [
										{
											"key": "id",
											"value": "1"
										}
									]
								}
							},
							"response": []
						}
					]
				},
				{
					"name": "CertificationsExperience",
					"item": [
						{
							"name": "Create CertificationsExperience",
							"request": {
								"method": "POST",
								"header": [
									{
										"key": "authorization",
										"value": "{{auth_jwt}}",
										"type": "text"
									},
									{
										"key": "x-api-key",
										"value": "{{secret_api_key}}",
										"type": "text"
									}
								],
								"body": {
									"mode": "raw",
									"raw": "{\n  \"supplier_id\": 5,\n  \"start_date\": \"2020-01-01\",\n  //\"end_date\": \"2022-12-31\",\n  \"name\": \"Certificación en Medicina General\",\n  \"company_name\": \"Universidad de Costa Rica\",\n  //\"province\": \"San José\",\n  //\"address\": \"Av. Central, Edificio Principal\",\n  //\"city_name\": \"San José\",\n  //\"country_iso_code\": \"CR\",\n  //\"is_currently\": false,\n  //\"url_document\": \"https://cdn.ejemplo.com/docs/certificado-123.pdf\",\n  \"experience_type_code\": \"CERTIFICATION\" //EXPERIENCE, EDUCATION, CERTIFICATION, AWARD_RECOGNITION, ACCREDITATION, SCIENTIFIC_PUBLICATION, CONFERENCE_PARTICIPATION, MEDICAL_RESEARCH\n}",
									"options": {
										"raw": {
											"language": "json"
										}
									}
								},
								"url": {
									"raw": "{{host}}/certificationsexperience/add",
									"host": [
										"{{host}}"
									],
									"path": [
										"certificationsexperience",
										"add"
									]
								}
							},
							"response": []
						},
						{
							"name": "Update CertificationsExperience",
							"request": {
								"method": "PUT",
								"header": [
									{
										"key": "authorization",
										"value": "{{auth_jwt}}",
										"type": "text"
									},
									{
										"key": "x-api-key",
										"value": "{{secret_api_key}}",
										"type": "text"
									}
								],
								"body": {
									"mode": "raw",
									"raw": "{\n  //\"supplier_id\": 5,\n  //\"start_date\": \"2020-01-01\",\n  //\"end_date\": \"2022-12-31\",\n  //\"name\": \"Certificación en Medicina General\",\n  //\"company_name\": \"Universidad de Costa Rica\",\n  //\"province\": \"San José\",\n  //\"address\": \"Av. Central, Edificio Principal\",\n  //\"city_name\": \"San José\",\n  //\"country_iso_code\": \"CR\",\n  //\"is_currently\": false,\n  \"url_document\": \"https://cdn.com/test.pdf\"\n //\"experience_type_code\": \"CERTIFICATION\" //EXPERIENCE, EDUCATION, CERTIFICATION, AWARD_RECOGNITION, ACCREDITATION, SCIENTIFIC_PUBLICATION, CONFERENCE_PARTICIPATION, MEDICAL_RESEARCH\n}",
									"options": {
										"raw": {
											"language": "json"
										}
									}
								},
								"url": {
									"raw": "{{host}}/certificationsexperience/edit?id=8",
									"host": [
										"{{host}}"
									],
									"path": [
										"certificationsexperience",
										"edit"
									],
									"query": [
										{
											"key": "id",
											"value": "8"
										}
									]
								}
							},
							"response": []
						},
						{
							"name": "Get CertificationsExperience by ID",
							"request": {
								"method": "GET",
								"header": [
									{
										"key": "authorization",
										"value": "{{auth_jwt}}",
										"type": "text"
									},
									{
										"key": "x-api-key",
										"value": "{{secret_api_key}}",
										"type": "text"
									}
								],
								"url": {
									"raw": "{{host}}/certificationsexperience/get?id=8",
									"host": [
										"{{host}}"
									],
									"path": [
										"certificationsexperience",
										"get"
									],
									"query": [
										{
											"key": "id",
											"value": "8"
										}
									]
								}
							},
							"response": []
						},
						{
							"name": "Get All CertificationsExperience",
							"request": {
								"method": "GET",
								"header": [
									{
										"key": "authorization",
										"value": "{{auth_jwt}}",
										"type": "text"
									},
									{
										"key": "x-api-key",
										"value": "{{secret_api_key}}",
										"type": "text"
									}
								],
								"url": {
									"raw": "{{host}}/certificationsexperience/get_all",
									"host": [
										"{{host}}"
									],
									"path": [
										"certificationsexperience",
										"get_all"
									]
								}
							},
							"response": []
						},
						{
							"name": "Delete CertificationsExperience",
							"request": {
								"method": "DELETE",
								"header": [
									{
										"key": "authorization",
										"value": "{{auth_jwt}}",
										"type": "text"
									},
									{
										"key": "x-api-key",
										"value": "{{secret_api_key}}",
										"type": "text"
									}
								],
								"url": {
									"raw": "{{host}}/certificationsexperience/delete?id=1",
									"host": [
										"{{host}}"
									],
									"path": [
										"certificationsexperience",
										"delete"
									],
									"query": [
										{
											"key": "id",
											"value": "1"
										}
									]
								}
							},
							"response": []
						}
					]
				},
				{
					"name": "LanguageSupplier",
					"item": [
						{
							"name": "Create LanguageSupplier",
							"request": {
								"method": "POST",
								"header": [
									{
										"key": "authorization",
										"value": "{{auth_jwt}}",
										"type": "text"
									},
									{
										"key": "x-api-key",
										"value": "{{secret_api_key}}",
										"type": "text"
									}
								],
								"body": {
									"mode": "raw",
									"raw": "{\n  \"supplier_id\": 5,\n  \"language_proficiency_code\": \"ADVANCED\",\n  \"language_code\": \"en\"\n}",
									"options": {
										"raw": {
											"language": "json"
										}
									}
								},
								"url": {
									"raw": "{{host}}/languagesupplier/add",
									"host": [
										"{{host}}"
									],
									"path": [
										"languagesupplier",
										"add"
									]
								}
							},
							"response": []
						},
						{
							"name": "Update LanguageSupplier",
							"request": {
								"method": "PUT",
								"header": [
									{
										"key": "authorization",
										"value": "{{auth_jwt}}",
										"type": "text"
									},
									{
										"key": "x-api-key",
										"value": "{{secret_api_key}}",
										"type": "text"
									}
								],
								"body": {
									"mode": "raw",
									"raw": "{\n  \"supplier_id\": 5,\n  \"language_proficiency_code\": \"ADVANCED\",\n  \"language_code\": \"fr\"\n}",
									"options": {
										"raw": {
											"language": "json"
										}
									}
								},
								"url": {
									"raw": "{{host}}/languagesupplier/edit?id=1",
									"host": [
										"{{host}}"
									],
									"path": [
										"languagesupplier",
										"edit"
									],
									"query": [
										{
											"key": "id",
											"value": "1"
										}
									]
								}
							},
							"response": []
						},
						{
							"name": "Get LanguageSupplier by ID",
							"request": {
								"method": "GET",
								"header": [
									{
										"key": "authorization",
										"value": "{{auth_jwt}}",
										"type": "text"
									},
									{
										"key": "x-api-key",
										"value": "{{secret_api_key}}",
										"type": "text"
									}
								],
								"url": {
									"raw": "{{host}}/languagesupplier/get?id=1",
									"host": [
										"{{host}}"
									],
									"path": [
										"languagesupplier",
										"get"
									],
									"query": [
										{
											"key": "id",
											"value": "1"
										}
									]
								}
							},
							"response": []
						},
						{
							"name": "Get All LanguageSupplier",
							"request": {
								"method": "GET",
								"header": [
									{
										"key": "authorization",
										"value": "{{auth_jwt}}",
										"type": "text"
									},
									{
										"key": "x-api-key",
										"value": "{{secret_api_key}}",
										"type": "text"
									}
								],
								"url": {
									"raw": "{{host}}/languagesupplier/get_all",
									"host": [
										"{{host}}"
									],
									"path": [
										"languagesupplier",
										"get_all"
									]
								}
							},
							"response": []
						},
						{
							"name": "Delete LanguageSupplier",
							"request": {
								"method": "DELETE",
								"header": [
									{
										"key": "authorization",
										"value": "{{auth_jwt}}",
										"type": "text"
									},
									{
										"key": "x-api-key",
										"value": "{{secret_api_key}}",
										"type": "text"
									}
								],
								"url": {
									"raw": "{{host}}/languagesupplier/delete?id=1",
									"host": [
										"{{host}}"
									],
									"path": [
										"languagesupplier",
										"delete"
									],
									"query": [
										{
											"key": "id",
											"value": "1"
										}
									]
								}
							},
							"response": []
						}
					]
				},
				{
					"name": "Review",
					"item": [
						{
							"name": "Create Review",
							"request": {
								"method": "POST",
								"header": [
									{
										"key": "authorization",
										"value": "{{auth_jwt}}",
										"type": "text"
									},
									{
										"key": "x-api-key",
										"value": "{{secret_api_key}}",
										"type": "text"
									}
								],
								"body": {
									"mode": "raw",
									"raw": "{\n  \"customer_id\": \"f1635823-7d9a-4df9-bd1e-ad8bd985de0b\",\n  \"appointment_id\": 1,\n  \"comment\": \"Excelente atención, muy profesional.\"\n  //\"is_annonymous\": false,\n  //\"supplier_reply\": \"Gracias por tu comentario. Siempre a la orden.\"\n}",
									"options": {
										"raw": {
											"language": "json"
										}
									}
								},
								"url": {
									"raw": "{{host}}/review/add",
									"host": [
										"{{host}}"
									],
									"path": [
										"review",
										"add"
									]
								}
							},
							"response": []
						},
						{
							"name": "Update Review",
							"request": {
								"method": "PUT",
								"header": [
									{
										"key": "authorization",
										"value": "{{auth_jwt}}",
										"type": "text"
									},
									{
										"key": "x-api-key",
										"value": "{{secret_api_key}}",
										"type": "text"
									}
								],
								"body": {
									"mode": "raw",
									"raw": "{\n  //\"customer_id\": \"f1635823-7d9a-4df9-bd1e-ad8bd985de0b\",\n  //\"appointment_id\": 1,\n  //\"comment\": \"Excelente atención, muy profesional.\"\n  //\"is_annonymous\": false,\n  \"supplier_reply\": \"Gracias por tu comentario. Siempre a la orden.\"\n}",
									"options": {
										"raw": {
											"language": "json"
										}
									}
								},
								"url": {
									"raw": "{{host}}/review/edit?id=6",
									"host": [
										"{{host}}"
									],
									"path": [
										"review",
										"edit"
									],
									"query": [
										{
											"key": "id",
											"value": "6"
										}
									]
								}
							},
							"response": []
						},
						{
							"name": "Get Review by ID",
							"request": {
								"method": "GET",
								"header": [
									{
										"key": "authorization",
										"value": "{{auth_jwt}}",
										"type": "text"
									},
									{
										"key": "x-api-key",
										"value": "{{secret_api_key}}",
										"type": "text"
									}
								],
								"url": {
									"raw": "{{host}}/review/get?id=6",
									"host": [
										"{{host}}"
									],
									"path": [
										"review",
										"get"
									],
									"query": [
										{
											"key": "id",
											"value": "6"
										}
									]
								}
							},
							"response": []
						},
						{
							"name": "Get All Review",
							"request": {
								"method": "GET",
								"header": [
									{
										"key": "authorization",
										"value": "{{auth_jwt}}",
										"type": "text"
									},
									{
										"key": "x-api-key",
										"value": "{{secret_api_key}}",
										"type": "text"
									}
								],
								"url": {
									"raw": "{{host}}/review/get_all",
									"host": [
										"{{host}}"
									],
									"path": [
										"review",
										"get_all"
									]
								}
							},
							"response": []
						},
						{
							"name": "Delete Review",
							"request": {
								"method": "DELETE",
								"header": [
									{
										"key": "authorization",
										"value": "{{auth_jwt}}",
										"type": "text"
									},
									{
										"key": "x-api-key",
										"value": "{{secret_api_key}}",
										"type": "text"
									}
								],
								"url": {
									"raw": "{{host}}/review/delete?id=1",
									"host": [
										"{{host}}"
									],
									"path": [
										"review",
										"delete"
									],
									"query": [
										{
											"key": "id",
											"value": "1"
										}
									]
								}
							},
							"response": []
						}
					]
				},
				{
					"name": "ReviewDetail",
					"item": [
						{
							"name": "Create ReviewDetail",
							"request": {
								"method": "POST",
								"header": [
									{
										"key": "authorization",
										"value": "{{auth_jwt}}",
										"type": "text"
									},
									{
										"key": "x-api-key",
										"value": "{{secret_api_key}}",
										"type": "text"
									}
								],
								"body": {
									"mode": "raw",
									"raw": "{\n  \"review_id\": 1,\n  \"stars_point\": 5,\n  \"review_code\": \"QUALITY_PRICE_RATIO\"\n}",
									"options": {
										"raw": {
											"language": "json"
										}
									}
								},
								"url": {
									"raw": "{{host}}/reviewdetail/add",
									"host": [
										"{{host}}"
									],
									"path": [
										"reviewdetail",
										"add"
									]
								}
							},
							"response": []
						},
						{
							"name": "Update ReviewDetail",
							"request": {
								"method": "PUT",
								"header": [
									{
										"key": "authorization",
										"value": "{{auth_jwt}}",
										"type": "text"
									},
									{
										"key": "x-api-key",
										"value": "{{secret_api_key}}",
										"type": "text"
									}
								],
								"body": {
									"mode": "raw",
									"raw": "{\n  \"review\": \"Test review 77\",\n  \"stars_point\": 3.5,\n  \"review_code\": \"QUALITY_PRICE_RATIO\"\n}",
									"options": {
										"raw": {
											"language": "json"
										}
									}
								},
								"url": {
									"raw": "{{host}}/reviewdetail/edit?id=16",
									"host": [
										"{{host}}"
									],
									"path": [
										"reviewdetail",
										"edit"
									],
									"query": [
										{
											"key": "id",
											"value": "16"
										}
									]
								}
							},
							"response": []
						},
						{
							"name": "Get ReviewDetail by ID",
							"request": {
								"method": "GET",
								"header": [
									{
										"key": "authorization",
										"value": "{{auth_jwt}}",
										"type": "text"
									},
									{
										"key": "x-api-key",
										"value": "{{secret_api_key}}",
										"type": "text"
									}
								],
								"url": {
									"raw": "{{host}}/reviewdetail/get?id=2",
									"host": [
										"{{host}}"
									],
									"path": [
										"reviewdetail",
										"get"
									],
									"query": [
										{
											"key": "id",
											"value": "2"
										}
									]
								}
							},
							"response": []
						},
						{
							"name": "Get All ReviewDetail",
							"request": {
								"method": "GET",
								"header": [
									{
										"key": "authorization",
										"value": "{{auth_jwt}}",
										"type": "text"
									},
									{
										"key": "x-api-key",
										"value": "{{secret_api_key}}",
										"type": "text"
									}
								],
								"url": {
									"raw": "{{host}}/reviewdetail/get_all",
									"host": [
										"{{host}}"
									],
									"path": [
										"reviewdetail",
										"get_all"
									]
								}
							},
							"response": []
						},
						{
							"name": "Delete ReviewDetail",
							"request": {
								"method": "DELETE",
								"header": [
									{
										"key": "authorization",
										"value": "{{auth_jwt}}",
										"type": "text"
									},
									{
										"key": "x-api-key",
										"value": "{{secret_api_key}}",
										"type": "text"
									}
								],
								"url": {
									"raw": "{{host}}/reviewdetail/delete?id=1",
									"host": [
										"{{host}}"
									],
									"path": [
										"reviewdetail",
										"delete"
									],
									"query": [
										{
											"key": "id",
											"value": "1"
										}
									]
								}
							},
							"response": []
						}
					]
				},
				{
					"name": "PreRegisterUser",
					"item": [
						{
							"name": "Create PreRegisterUser",
							"request": {
								"method": "POST",
								"header": [
									{
										"key": "authorization",
										"value": "{{auth_jwt}}",
										"type": "text"
									},
									{
										"key": "x-api-key",
										"value": "{{secret_api_key}}",
										"type": "text"
									}
								],
								"body": {
									"mode": "raw",
									"raw": "{\n  \"card_id\": \"11777\",\n  \"id_type\": \"PHYSICAL_DNI\",\n  \"name\": \"Fabian Esq\",\n  //\"address\": \"Heredia Costa Rica\",\n  //\"birth_date\": \"1993-05-07\",\n  \"finance_entity\": \"8401b1be-7e1d-4357-a632-15172a647b8d\"\n}",
									"options": {
										"raw": {
											"language": "json"
										}
									}
								},
								"url": {
									"raw": "{{host}}/preregisteruser/add",
									"host": [
										"{{host}}"
									],
									"path": [
										"preregisteruser",
										"add"
									]
								}
							},
							"response": []
						},
						{
							"name": "Update PreRegisterUser",
							"request": {
								"method": "PUT",
								"header": [
									{
										"key": "authorization",
										"value": "{{auth_jwt}}",
										"type": "text"
									},
									{
										"key": "x-api-key",
										"value": "{{secret_api_key}}",
										"type": "text"
									}
								],
								"body": {
									"mode": "raw",
									"raw": "{\n  \"card_id\": \"11777\",\n  \"id_type\": \"PHYSICAL_DNI\",\n  \"name\": \"Fabian Esq\",\n  \"address\": \"Heredia Costa Rica\",\n  \"birth_date\": \"1993-05-07\",\n  \"finance_entity\": \"8401b1be-7e1d-4357-a632-15172a647b8d\"\n}",
									"options": {
										"raw": {
											"language": "json"
										}
									}
								},
								"url": {
									"raw": "{{host}}/preregisteruser/edit?id=1",
									"host": [
										"{{host}}"
									],
									"path": [
										"preregisteruser",
										"edit"
									],
									"query": [
										{
											"key": "id",
											"value": "1"
										}
									]
								}
							},
							"response": []
						},
						{
							"name": "Get PreRegisterUser by ID",
							"request": {
								"method": "GET",
								"header": [
									{
										"key": "authorization",
										"value": "{{auth_jwt}}",
										"type": "text"
									},
									{
										"key": "x-api-key",
										"value": "{{secret_api_key}}",
										"type": "text"
									}
								],
								"url": {
									"raw": "{{host}}/preregisteruser/get?id=1",
									"host": [
										"{{host}}"
									],
									"path": [
										"preregisteruser",
										"get"
									],
									"query": [
										{
											"key": "id",
											"value": "1"
										}
									]
								}
							},
							"response": []
						},
						{
							"name": "Get All PreRegisterUser",
							"request": {
								"method": "GET",
								"header": [
									{
										"key": "authorization",
										"value": "{{auth_jwt}}",
										"type": "text"
									},
									{
										"key": "x-api-key",
										"value": "{{secret_api_key}}",
										"type": "text"
									}
								],
								"url": {
									"raw": "{{host}}/preregisteruser/get_all",
									"host": [
										"{{host}}"
									],
									"path": [
										"preregisteruser",
										"get_all"
									]
								}
							},
							"response": []
						},
						{
							"name": "Delete PreRegisterUser",
							"request": {
								"method": "DELETE",
								"header": [
									{
										"key": "authorization",
										"value": "{{auth_jwt}}",
										"type": "text"
									},
									{
										"key": "x-api-key",
										"value": "{{secret_api_key}}",
										"type": "text"
									}
								],
								"url": {
									"raw": "{{host}}/preregisteruser/delete?id=1",
									"host": [
										"{{host}}"
									],
									"path": [
										"preregisteruser",
										"delete"
									],
									"query": [
										{
											"key": "id",
											"value": "1"
										}
									]
								}
							},
							"response": []
						}
					]
				},
				{
					"name": "Appointment",
					"item": [
						{
							"name": "Create Appointment",
							"request": {
								"method": "POST",
								"header": [
									{
										"key": "authorization",
										"value": "{{auth_jwt}}",
										"type": "text"
									},
									{
										"key": "x-api-key",
										"value": "{{secret_api_key}}",
										"type": "text"
									}
								],
								"body": {
									"mode": "raw",
									"raw": "{\n  \"customer_id\": \"f1635823-7d9a-4df9-bd1e-ad8bd985de0b\",\n  //\"proforma_file_code\": \"PROF-011\",\n  \"appointment_date\": \"2025-04-14\",\n  \"appointment_hour\": \"09:30:00\",\n  \"reservation_type_code\": \"RESERVATION\",\n  //\"appointment_status_code\": \"PENDING\",\n  \"supplier_id\": 1\n  //\"package_id\": 1,\n  //\"procedure_id\": 1\n  //\"application_date\": \"2025-04-12T08:00:00.000Z\",\n  //\"payment_status_code\": \"PENDING\",\n  //\"payment_method_code\": \"CREDIT_CARD\",\n  //\"appointment_result_code\": \"FIT_FOR_PROCEDURE\",\n  //\"user_description\": \"Consulta general preventiva.\",\n  //\"recommendation_post_appointment\": \"Mantener una dieta balanceada.\",\n  //\"diagnostic\": \"Salud estable.\"\n  //\"is_for_external_user\": false,\n  // \"phone_number_external_user\":\"+506 8346-1166\"\n}\n\n\n",
									"options": {
										"raw": {
											"language": "json"
										}
									}
								},
								"url": {
									"raw": "{{host}}/appointment/add",
									"host": [
										"{{host}}"
									],
									"path": [
										"appointment",
										"add"
									]
								}
							},
							"response": []
						},
						{
							"name": "Create Appointment Example",
							"request": {
								"method": "POST",
								"header": [
									{
										"key": "authorization",
										"value": "{{auth_jwt}}",
										"type": "text"
									},
									{
										"key": "x-api-key",
										"value": "{{secret_api_key}}",
										"type": "text"
									}
								],
								"body": {
									"mode": "raw",
									"raw": "{\n  \"customer_id\": \"f1635823-7d9a-4df9-bd1e-ad8bd985de0b\",\n  //\"is_for_external_user\": false, //default false\n  //\"phone_number_external_user\":\"+506 8346-1166\"\n  \"user_description\": \"Consulta gOftalmologica\",\n  \"supplier_id\": 1,\n  \"appointment_date\": \"2025-04-14\",\n  \"appointment_hour\": \"09:30:00\",\n  //\"procedure_id\": 1,\n  \"package_id\": 1\n}",
									"options": {
										"raw": {
											"language": "json"
										}
									}
								},
								"url": {
									"raw": "{{host}}/appointment/add",
									"host": [
										"{{host}}"
									],
									"path": [
										"appointment",
										"add"
									]
								}
							},
							"response": []
						},
						{
							"name": "Update Appointment",
							"request": {
								"method": "PUT",
								"header": [
									{
										"key": "authorization",
										"value": "{{auth_jwt}}",
										"type": "text"
									},
									{
										"key": "x-api-key",
										"value": "{{secret_api_key}}",
										"type": "text"
									}
								],
								"body": {
									"mode": "raw",
									"raw": "{\n  \"customer_id\": \"f1635823-7d9a-4df9-bd1e-ad8bd985de0b\",\n  //\"proforma_file_code\": \"PROF-011\",\n  \"appointment_date\": \"2025-04-14\",\n  \"appointment_hour\": \"09:30:00\",\n  \"reservation_type\": \"RESERVATION\",\n  //\"appointment_status_code\": \"PENDING\",\n  \"supplier_id\": 1\n  //\"package_id\": 1,\n  //\"procedure_id\": 1\n  //\"application_date\": \"2025-04-12T08:00:00.000Z\",\n  //\"payment_status_code\": \"PENDING\",\n  //\"payment_method_code\": \"CREDIT_CARD\",\n  //\"appointment_result_code\": \"FIT_FOR_PROCEDURE\",\n  //\"user_description\": \"Consulta general preventiva.\",\n  //\"recommendation_post_appointment\": \"Mantener una dieta balanceada.\",\n  //\"diagnostic\": \"Salud estable.\",\n   //\"is_for_external_user\": false,\n  // \"phone_number_external_user\":\"+506 8346-1166\"\n}\n",
									"options": {
										"raw": {
											"language": "json"
										}
									}
								},
								"url": {
									"raw": "{{host}}/appointment/edit?id=1",
									"host": [
										"{{host}}"
									],
									"path": [
										"appointment",
										"edit"
									],
									"query": [
										{
											"key": "id",
											"value": "1"
										}
									]
								}
							},
							"response": []
						},
						{
							"name": "Update Appointment Example Cancel",
							"request": {
								"method": "PUT",
								"header": [
									{
										"key": "authorization",
										"value": "{{auth_jwt}}",
										"type": "text"
									},
									{
										"key": "x-api-key",
										"value": "{{secret_api_key}}",
										"type": "text"
									}
								],
								"body": {
									"mode": "raw",
									"raw": "{\n  \"appointment_status_code\": \"CANCEL\",\n  \"payment_status_code\": \"NOT_PAID\"\n}\n",
									"options": {
										"raw": {
											"language": "json"
										}
									}
								},
								"url": {
									"raw": "{{host}}/appointment/edit?id=2",
									"host": [
										"{{host}}"
									],
									"path": [
										"appointment",
										"edit"
									],
									"query": [
										{
											"key": "id",
											"value": "2"
										}
									]
								}
							},
							"response": []
						},
						{
							"name": "Get Appointment by ID",
							"request": {
								"method": "GET",
								"header": [
									{
										"key": "authorization",
										"value": "{{auth_jwt}}",
										"type": "text"
									},
									{
										"key": "x-api-key",
										"value": "{{secret_api_key}}",
										"type": "text"
									}
								],
								"url": {
									"raw": "{{host}}/appointment/get?id=1",
									"host": [
										"{{host}}"
									],
									"path": [
										"appointment",
										"get"
									],
									"query": [
										{
											"key": "id",
											"value": "1"
										}
									]
								}
							},
							"response": []
						},
						{
							"name": "Get All Appointment",
							"request": {
								"method": "GET",
								"header": [
									{
										"key": "authorization",
										"value": "{{auth_jwt}}",
										"type": "text"
									},
									{
										"key": "x-api-key",
										"value": "{{secret_api_key}}",
										"type": "text"
									}
								],
								"url": {
									"raw": "{{host}}/appointment/get_all",
									"host": [
										"{{host}}"
									],
									"path": [
										"appointment",
										"get_all"
									]
								}
							},
							"response": []
						},
						{
							"name": "Delete Appointment",
							"request": {
								"method": "DELETE",
								"header": [
									{
										"key": "authorization",
										"value": "{{auth_jwt}}",
										"type": "text"
									},
									{
										"key": "x-api-key",
										"value": "{{secret_api_key}}",
										"type": "text"
									}
								],
								"url": {
									"raw": "{{host}}/appointment/delete?id=3",
									"host": [
										"{{host}}"
									],
									"path": [
										"appointment",
										"delete"
									],
									"query": [
										{
											"key": "id",
											"value": "3"
										}
									]
								}
							},
							"response": []
						}
					]
				},
				{
					"name": "AppointmentCredit",
					"item": [
						{
							"name": "Create AppointmentCredit",
							"request": {
								"method": "POST",
								"header": [
									{
										"key": "authorization",
										"value": "{{auth_jwt}}",
										"type": "text"
									},
									{
										"key": "x-api-key",
										"value": "{{secret_api_key}}",
										"type": "text"
									}
								],
								"body": {
									"mode": "raw",
									"raw": "{\n  \"appointment\": 1,\n  \"credit_status\": \"REQUIRED\"\n  //\"requested_amount\": \"1500.00\",\n  //\"approved_amount\": \"1200.00\",\n  //\"credit_observations\": \"Solicitud en evaluación.\",\n  //\"pagare_file_code\": \"PAGARE-TEST-001\"\n}\n",
									"options": {
										"raw": {
											"language": "json"
										}
									}
								},
								"url": {
									"raw": "{{host}}/appointmentcredit/add",
									"host": [
										"{{host}}"
									],
									"path": [
										"appointmentcredit",
										"add"
									]
								}
							},
							"response": []
						},
						{
							"name": "Update AppointmentCredit",
							"request": {
								"method": "PUT",
								"header": [
									{
										"key": "authorization",
										"value": "{{auth_jwt}}",
										"type": "text"
									},
									{
										"key": "x-api-key",
										"value": "{{secret_api_key}}",
										"type": "text"
									}
								],
								"body": {
									"mode": "raw",
									"raw": "{\n  \"appointment\": 1,\n  \"credit_status\": \"REQUIRED\"\n  //\"requested_amount\": \"1500.00\",\n  //\"approved_amount\": \"1200.00\",\n  //\"credit_observations\": \"Solicitud en evaluación.\",\n  //\"pagare_file_code\": \"PAGARE-TEST-001\"\n}\n",
									"options": {
										"raw": {
											"language": "json"
										}
									}
								},
								"url": {
									"raw": "{{host}}/appointmentcredit/edit?id=1",
									"host": [
										"{{host}}"
									],
									"path": [
										"appointmentcredit",
										"edit"
									],
									"query": [
										{
											"key": "id",
											"value": "1"
										}
									]
								}
							},
							"response": []
						},
						{
							"name": "Get AppointmentCredit by ID",
							"request": {
								"method": "GET",
								"header": [
									{
										"key": "authorization",
										"value": "{{auth_jwt}}",
										"type": "text"
									},
									{
										"key": "x-api-key",
										"value": "{{secret_api_key}}",
										"type": "text"
									}
								],
								"url": {
									"raw": "{{host}}/appointmentcredit/get?id=1",
									"host": [
										"{{host}}"
									],
									"path": [
										"appointmentcredit",
										"get"
									],
									"query": [
										{
											"key": "id",
											"value": "1"
										}
									]
								}
							},
							"response": []
						},
						{
							"name": "Get All AppointmentCredit",
							"request": {
								"method": "GET",
								"header": [
									{
										"key": "authorization",
										"value": "{{auth_jwt}}",
										"type": "text"
									},
									{
										"key": "x-api-key",
										"value": "{{secret_api_key}}",
										"type": "text"
									}
								],
								"url": {
									"raw": "{{host}}/appointmentcredit/get_all",
									"host": [
										"{{host}}"
									],
									"path": [
										"appointmentcredit",
										"get_all"
									]
								}
							},
							"response": []
						},
						{
							"name": "Delete AppointmentCredit",
							"request": {
								"method": "DELETE",
								"header": [
									{
										"key": "authorization",
										"value": "{{auth_jwt}}",
										"type": "text"
									},
									{
										"key": "x-api-key",
										"value": "{{secret_api_key}}",
										"type": "text"
									}
								],
								"url": {
									"raw": "{{host}}/appointmentcredit/delete?id=1",
									"host": [
										"{{host}}"
									],
									"path": [
										"appointmentcredit",
										"delete"
									],
									"query": [
										{
											"key": "id",
											"value": "1"
										}
									]
								}
							},
							"response": []
						}
					]
				}
			]
		}
	]
}